_examples/__init__.py
examples/__init__.py
tests/__init__.py
tests/test_main.py
tests/test_sbatch.py
tests/interactive/__init__.py
tests/interactive/cancel.py
tests/interactive/get.py
tests/interactive/job_status.py
tests/interactive/put.py
tests/interactive/put_sbatch.py
tests/interactive/run.py
ufrc/__init__.py
ufrc/exc.py
ufrc/main.py
ufrc/sbatch.py
ufrc/squeue/__init__.py
ufrc/squeue/model.py
ufrc/ssh/__init__.py
ufrc/ssh/client.py
ufrc/ssh/response.py
ufrc-0.2.3.dist-info/LICENSE.md
ufrc-0.2.3.dist-info/METADATA
ufrc-0.2.3.dist-info/WHEEL
ufrc-0.2.3.dist-info/entry_points.txt
ufrc-0.2.3.dist-info/top_level.txt
ufrc-0.2.3.dist-info/RECORD
