Metadata-Version: 2.1
Name: ufrc
Version: 0.2.3
Summary: Tools for UFRC
Home-page: https://github.com/nickderobertis/ufrc
Author: Nick DeRobertis
Author-email: whoopnip@gmail.com
License: MIT
Project-URL: Code, https://github.com/nickderobertis/ufrc
Project-URL: Documentation, https://nickderobertis.github.io/ufrc
Platform: UNKNOWN
Classifier: Development Status :: 3 - Alpha
Classifier: Intended Audience :: Developers
Classifier: Programming Language :: Python :: 3.6
Classifier: Programming Language :: Python :: 3.7
License-File: LICENSE.md
Requires-Dist: paramiko
Requires-Dist: scp
